Metadata-Version: 2.1
Name: odoo14-addon-web_view_google_map
Version: 14.0.1.0.1.dev6
Summary: Add a Google Map view type to the Odoo web client
Home-page: https://github.com/OCA/geospatial
Author: Open Source Integrators, Odoo Community Association (OCA)
Author-email: support@odoo-community.org
License: AGPL-3
Classifier: Programming Language :: Python
Classifier: Framework :: Odoo
Classifier: Framework :: Odoo :: 14.0
Classifier: License :: OSI Approved :: GNU Affero General Public License v3
Requires-Python: >=3.6
Requires-Dist: odoo14-addon-base-google-map
Requires-Dist: odoo<14.1dev,>=14.0a
